aiohomeconnect/__init__.py
aiohomeconnect/__main__.py
aiohomeconnect/client.py
aiohomeconnect/const.py
aiohomeconnect/py.typed
aiohomeconnect/cli/__init__.py
aiohomeconnect/cli/client.py
aiohomeconnect/model/__init__.py
aiohomeconnect/model/appliance.py
aiohomeconnect/model/command.py
aiohomeconnect/model/error.py
aiohomeconnect/model/event.py
aiohomeconnect/model/image.py
aiohomeconnect/model/program.py
aiohomeconnect/model/setting.py
aiohomeconnect/model/status.py
aiohomeconnect-0.28.0.dist-info/licenses/LICENSE
aiohomeconnect-0.28.0.dist-info/METADATA
aiohomeconnect-0.28.0.dist-info/WHEEL
aiohomeconnect-0.28.0.dist-info/entry_points.txt
aiohomeconnect-0.28.0.dist-info/top_level.txt
aiohomeconnect-0.28.0.dist-info/RECORD
