Metadata-Version: 2.4
Name: aiohomeconnect
Version: 0.28.0
Summary: An asyncio client for the Home Connect API.
Author-email: Martin Hjelmare <marhje52@gmail.com>
License: Apache-2.0
Project-URL: Bug Tracker, https://github.com/MartinHjelmare/aiohomeconnect/issues
Project-URL: Changelog, https://github.com/MartinHjelmare/aiohomeconnect/blob/main/CHANGELOG.md
Project-URL: documentation, https://aiohomeconnect.readthedocs.io
Project-URL: repository, https://github.com/MartinHjelmare/aiohomeconnect
Classifier: Development Status :: 2 - Pre-Alpha
Classifier: Intended Audience :: Developers
Classifier: Natural Language :: English
Classifier: Operating System :: OS Independent
Classifier: Programming Language :: Python :: 3.11
Classifier: Programming Language :: Python :: 3.12
Classifier: Programming Language :: Python :: 3.13
Classifier: Topic :: Software Development :: Libraries
Requires-Python: >=3.11
License-File: LICENSE
Requires-Dist: httpx<1,>=0.28.0
Requires-Dist: httpx-sse<1,>=0.4.0
Requires-Dist: mashumaro<4,>=3.13.1
Provides-Extra: cli
Requires-Dist: authlib<2,>=1.3.0; extra == "cli"
Requires-Dist: fastapi<1,>=0.115.0; extra == "cli"
Requires-Dist: uvicorn<1,>=0.34.0; extra == "cli"
Requires-Dist: typer<1,>=0.15; extra == "cli"
Dynamic: license-file
